{
  "GET /health": "Returns health status",
  "GET /stations": "Query: date",
  "GET /aqi/predict": "Query: date",
  "GET /aqi/trend": "Query: date, station",
  "GET /hotspots": "Query: date, threshold",
  "GET /hcho/grid": "Query: date",
  "GET /hcho/seasonal": "Query: year",
  "GET /fires": "Query: date, minFRP",
  "GET /fires/monthly": "Query: year",
  "GET /fires/summary": "Query: date",
  "GET /winds": "Query: date",
  "GET /trajectory": "Query: date",
  "GET /transport/stats": "Query: date",
  "GET /analytics/scatter": "Query: date",
  "GET /analytics/correlation": "Query: date",
  "GET /analytics/distribution": "Query: date",
  "GET /model/performance": "No params",
  "GET /model/loss-curve": "No params",
  "GET /model/residuals": "No params",
  "POST /config": "Payload: ConfigUpdate",
  "POST /location-analysis": "Payload: LocationAnalysisRequest",
  "GET /aqi": "Query: date",
  "GET /hcho": "Query: date",
  "GET /fire": "Query: date",
  "GET /weather": "Query: date",
  "GET /model-performance": "No params",
  "GET /system/gee-status": "No params",
  "GET /system/live-sentinel-test": "Query: lat, lon",
  "POST /predict/location": "Payload: LocationPredictRequest"
}
